ruamel.base-1.0.0-py3.4-nspkg.pth
ruamel.base-1.0.0.dist-info/namespace_packages.txt
ruamel.base-1.0.0.dist-info/WHEEL
ruamel.base-1.0.0.dist-info/top_level.txt
ruamel.base-1.0.0.dist-info/RECORD
ruamel.base-1.0.0.dist-info/metadata.json
ruamel.base-1.0.0.dist-info/METADATA
ruamel.base-1.0.0.dist-info/DESCRIPTION.rst
ruamel.base-1.0.0.dist-info/LICENSE.txt
ruamel/base/__init__.py
