Metadata-Version: 1.1
Name: ruamel.base
Version: 1.0.0
Summary: common routines for ruamel packages
Home-page: https://bitbucket.org/ruamel/base
Author: Anthon van der Neut
Author-email: a.van.der.neut@ruamel.eu
License: MIT license
Platform: UNKNOWN
Classifier: Development Status :: 4 - Beta
Classifier: Intended Audience :: Developers
Classifier: License :: OSI Approved :: MIT License
Classifier: Operating System :: OS Independent
Classifier: Programming Language :: Python
